LICENSE
MANIFEST.in
README.md
requirements.txt
setup.py
medAId.egg-info/PKG-INFO
medAId.egg-info/SOURCES.txt
medAId.egg-info/dependency_links.txt
medAId.egg-info/requires.txt
medAId.egg-info/top_level.txt
medaid/__init__.py
medaid/medaid.py
medaid.egg-info/PKG-INFO
medaid.egg-info/SOURCES.txt
medaid.egg-info/dependency_links.txt
medaid.egg-info/requires.txt
medaid.egg-info/top_level.txt
medaid/preprocessing/__init__.py
medaid/preprocessing/column_removal.py
medaid/preprocessing/encoder.py
medaid/preprocessing/imputer.py
medaid/preprocessing/numeric_format_handler.py
medaid/preprocessing/preprocessing.py
medaid/preprocessing/preprocessing_info.py
medaid/preprocessing/scaler.py
medaid/reporting/__init__.py
medaid/reporting/mainreporter.py
medaid/reporting/plots.py
medaid/reporting/predictexplain.py
medaid/training/__init__.py
medaid/training/search.py
medaid/training/train.py
tests/tests_preprocessing/test_imputer.py